Partial_Aligner/Aligner_script.py
Partial_Aligner/__init__.py
Partial_Aligner/_version.py
Partial_Aligner/utils.py
Partial_Aligner-0.0.1.dist-info/LICENSE
Partial_Aligner-0.0.1.dist-info/METADATA
Partial_Aligner-0.0.1.dist-info/WHEEL
Partial_Aligner-0.0.1.dist-info/entry_points.txt
Partial_Aligner-0.0.1.dist-info/top_level.txt
Partial_Aligner-0.0.1.dist-info/RECORD
