Metadata-Version: 2.1
Name: Partial-Aligner
Version: 0.0.1
Summary: A napari plugin for manual registration of (a part of) an image
Home-page: https://github.com/DKFZ-TMTRR/Partial-Aligner
Author: Marc Boucsein, Robin Koch
License: BSD-3
Platform: UNKNOWN
Classifier: Development Status :: 4 - Beta
Classifier: Intended Audience :: Developers
Classifier: Framework :: napari
Classifier: Topic :: Software Development :: Testing
Classifier: Programming Language :: Python
Classifier: Programming Language :: Python :: 3
Classifier: Programming Language :: Python :: 3.9
Classifier: Operating System :: OS Independent
Classifier: License :: OSI Approved :: BSD License
Requires-Python: >=3.9
License-File: LICENSE
Requires-Dist: napari-plugin-engine (>=0.1.4)
Requires-Dist: numpy
Requires-Dist: packaging
Requires-Dist: dask
